<?xml version="1.0" encoding="UTF-8"?>
<AssetDeclaration xmlns="uri:ea.com:eala:asset" xmlns:xsi="http://www.w3.org/2001/XMLSchema-instance">
	<AptAptData id="Timeline_apt" File="Timeline.apt"/>
	<AptConstData id="Timeline_const" File="Timeline.const"/>
	<AptDatData id="Timeline_dat" File="Timeline.dat"/>
	<AptGeometryData id="Timeline_1" File="Timeline_1.ru" AptID="1"/>
	<AptGeometryData id="Timeline_2" File="Timeline_2.ru" AptID="2"/>
	<AptGeometryData id="Timeline_7" File="Timeline_7.ru" AptID="7"/>
	<AptGeometryData id="Timeline_9" File="Timeline_9.ru" AptID="9"/>
	<AptGeometryData id="Timeline_12" File="Timeline_12.ru" AptID="12"/>
	<AptGeometryData id="Timeline_18" File="Timeline_18.ru" AptID="18"/>
	<AptGeometryData id="Timeline_22" File="Timeline_22.ru" AptID="22"/>
	<AptGeometryData id="Timeline_25" File="Timeline_25.ru" AptID="25"/>
	<AptGeometryData id="Timeline_30" File="Timeline_30.ru" AptID="30"/>
	<AptGeometryData id="Timeline_33" File="Timeline_33.ru" AptID="33"/>
	<AptGeometryData id="Timeline_40" File="Timeline_40.ru" AptID="40"/>
	<AptGeometryData id="Timeline_43" File="Timeline_43.ru" AptID="43"/>
	<AptGeometryData id="Timeline_46" File="Timeline_46.ru" AptID="46"/>
	<AptGeometryData id="Timeline_49" File="Timeline_49.ru" AptID="49"/>
	<AptGeometryData id="Timeline_54" File="Timeline_54.ru" AptID="54"/>
	<AptGeometryData id="Timeline_57" File="Timeline_57.ru" AptID="57"/>
	<AptGeometryData id="Timeline_60" File="Timeline_60.ru" AptID="60"/>
	<AptGeometryData id="Timeline_89" File="Timeline_89.ru" AptID="89"/>
	<AptGeometryData id="Timeline_91" File="Timeline_91.ru" AptID="91"/>
	<AptGeometryData id="Timeline_95" File="Timeline_95.ru" AptID="95"/>
	<AptGeometryData id="Timeline_97" File="Timeline_97.ru" AptID="97"/>
	<AptGeometryData id="Timeline_102" File="Timeline_102.ru" AptID="102"/>
	<AptGeometryData id="Timeline_105" File="Timeline_105.ru" AptID="105"/>
	<AptGeometryData id="Timeline_108" File="Timeline_108.ru" AptID="108"/>
	<AptGeometryData id="Timeline_111" File="Timeline_111.ru" AptID="111"/>
	<AptGeometryData id="Timeline_117" File="Timeline_117.ru" AptID="117"/>
	<AptGeometryData id="Timeline_121" File="Timeline_121.ru" AptID="121"/>
	<AptGeometryData id="Timeline_123" File="Timeline_123.ru" AptID="123"/>
	<AptGeometryData id="Timeline_126" File="Timeline_126.ru" AptID="126"/>
	<AptGeometryData id="Timeline_128" File="Timeline_128.ru" AptID="128"/>
	<AptGeometryData id="Timeline_136" File="Timeline_136.ru" AptID="136"/>
	<AptGeometryData id="Timeline_138" File="Timeline_138.ru" AptID="138"/>
	<AptGeometryData id="Timeline_141" File="Timeline_141.ru" AptID="141"/>
	<Texture id="apt_Timeline_1" File="ART:Firestorm\Misc\APTUI\Timeline\apt_Timeline_1.tga" OutputFormat="A8R8G8B8" GenerateMipMaps="false" AllowAutomaticResize="false"/>
</AssetDeclaration>
