<?xml version="1.0" encoding="UTF-8"?>
<AssetDeclaration xmlns="uri:ea.com:eala:asset" xmlns:xsi="http://www.w3.org/2001/XMLSchema-instance">
	<AudioFile id="TiberiumBomb_BigExplo" File="Bomb\TiberiumBomb_BigExplo.wav" PCCompression="XAS" GUIPreset="Default"/>

	<AudioFile id="AIShard_impacta" File="Impact\AIShard_impacta.wav" PCCompression="XAS" GUIPreset="Default"/>
	<AudioFile id="AIShard_impactb" File="Impact\AIShard_impactb.wav" PCCompression="XAS" GUIPreset="Default"/>
	<AudioFile id="AIShard_impactc" File="Impact\AIShard_impactc.wav" PCCompression="XAS" GUIPreset="Default"/>
	<AudioFile id="AIShard_impactd" File="Impact\AIShard_impactd.wav" PCCompression="XAS" GUIPreset="Default"/>
	<AudioFile id="AIShard_impacte" File="Impact\AIShard_impacte.wav" PCCompression="XAS" GUIPreset="Default"/>
	<AudioFile id="AIShard_impactf" File="Impact\AIShard_impactf.wav" PCCompression="XAS" GUIPreset="Default"/>
	<AudioFile id="AIShard_impactg" File="Impact\AIShard_impactg.wav" PCCompression="XAS" GUIPreset="Default"/>
	<AudioFile id="AIShard_impacth" File="Impact\AIShard_impacth.wav" PCCompression="XAS" GUIPreset="Default"/>
</AssetDeclaration>
