<?xml version="1.0" encoding="UTF-8"?>
<AssetDeclaration xmlns="uri:ea.com:eala:asset" xmlns:xsi="http://www.w3.org/2001/XMLSchema-instance">
	<AudioFile id="NUOblite_voiAttacka" File="Attack\NUOblite_voiAttacka.wav" PCCompression="XAS" GUIPreset="Default"/>
	<AudioFile id="NUOblite_voiAttackb" File="Attack\NUOblite_voiAttackb.wav" PCCompression="XAS" GUIPreset="Default"/>
	<AudioFile id="NUOblite_voiAttackc" File="Attack\NUOblite_voiAttackc.wav" PCCompression="XAS" GUIPreset="Default"/>
	<AudioFile id="NUOblite_voiAttackd" File="Attack\NUOblite_voiAttackd.wav" PCCompression="XAS" GUIPreset="Default"/>
	<AudioFile id="NUOblite_voiAttacke" File="Attack\NUOblite_voiAttacke.wav" PCCompression="XAS" GUIPreset="Default"/>
	<AudioFile id="NUOblite_voiAttackf" File="Attack\NUOblite_voiAttackf.wav" PCCompression="XAS" GUIPreset="Default"/>
	<AudioFile id="NUOblite_voiAttackg" File="Attack\NUOblite_voiAttackg.wav" PCCompression="XAS" GUIPreset="Default"/>

	<AudioFile id="NUOblite_voiMvAtta" File="AttackMove\NUOblite_voiMvAtta.wav" PCCompression="XAS" GUIPreset="Default"/>
	<AudioFile id="NUOblite_voiMvAttb" File="AttackMove\NUOblite_voiMvAttb.wav" PCCompression="XAS" GUIPreset="Default"/>
	<AudioFile id="NUOblite_voiMvAttc" File="AttackMove\NUOblite_voiMvAttc.wav" PCCompression="XAS" GUIPreset="Default"/>
	<AudioFile id="NUOblite_voiMvAttd" File="AttackMove\NUOblite_voiMvAttd.wav" PCCompression="XAS" GUIPreset="Default"/>
	<AudioFile id="NUOblite_voiMvAtte" File="AttackMove\NUOblite_voiMvAtte.wav" PCCompression="XAS" GUIPreset="Default"/>
	<AudioFile id="NUOblite_voiMvAttf" File="AttackMove\NUOblite_voiMvAttf.wav" PCCompression="XAS" GUIPreset="Default"/>

	<AudioFile id="NUOblite_voiCreatea" File="Create\NUOblite_voiCreatea.wav" PCCompression="XAS" GUIPreset="Default"/>
	<AudioFile id="NUOblite_voiCreateb" File="Create\NUOblite_voiCreateb.wav" PCCompression="XAS" GUIPreset="Default"/>

	<AudioFile id="NUOblite_voiMovea" File="Move\NUOblite_voiMovea.wav" PCCompression="XAS" GUIPreset="Default"/>
	<AudioFile id="NUOblite_voiMoveb" File="Move\NUOblite_voiMoveb.wav" PCCompression="XAS" GUIPreset="Default"/>
	<AudioFile id="NUOblite_voiMovec" File="Move\NUOblite_voiMovec.wav" PCCompression="XAS" GUIPreset="Default"/>
	<AudioFile id="NUOblite_voiMoved" File="Move\NUOblite_voiMoved.wav" PCCompression="XAS" GUIPreset="Default"/>
	<AudioFile id="NUOblite_voiMovee" File="Move\NUOblite_voiMovee.wav" PCCompression="XAS" GUIPreset="Default"/>
	<AudioFile id="NUOblite_voiMovef" File="Move\NUOblite_voiMovef.wav" PCCompression="XAS" GUIPreset="Default"/>
	<AudioFile id="NUOblite_voiMoveg" File="Move\NUOblite_voiMoveg.wav" PCCompression="XAS" GUIPreset="Default"/>
	<AudioFile id="NUOblite_voiMoveh" File="Move\NUOblite_voiMoveh.wav" PCCompression="XAS" GUIPreset="Default"/>
	<AudioFile id="NUOblite_voiMovei" File="Move\NUOblite_voiMovei.wav" PCCompression="XAS" GUIPreset="Default"/>

	<AudioFile id="NUOblite_voiRetreaa" File="Retreat\NUOblite_voiRetreaa.wav" PCCompression="XAS" GUIPreset="Default"/>
	<AudioFile id="NUOblite_voiRetreab" File="Retreat\NUOblite_voiRetreab.wav" PCCompression="XAS" GUIPreset="Default"/>
	<AudioFile id="NUOblite_voiRetreac" File="Retreat\NUOblite_voiRetreac.wav" PCCompression="XAS" GUIPreset="Default"/>

	<AudioFile id="NUOblite_voiSelecta" File="Select\NUOblite_voiSelecta.wav" PCCompression="XAS" GUIPreset="Default"/>
	<AudioFile id="NUOblite_voiSelectb" File="Select\NUOblite_voiSelectb.wav" PCCompression="XAS" GUIPreset="Default"/>
	<AudioFile id="NUOblite_voiSelectc" File="Select\NUOblite_voiSelectc.wav" PCCompression="XAS" GUIPreset="Default"/>
	<AudioFile id="NUOblite_voiSelectd" File="Select\NUOblite_voiSelectd.wav" PCCompression="XAS" GUIPreset="Default"/>
	<AudioFile id="NUOblite_voiSelecte" File="Select\NUOblite_voiSelecte.wav" PCCompression="XAS" GUIPreset="Default"/>
	<AudioFile id="NUOblite_voiSelectf" File="Select\NUOblite_voiSelectf.wav" PCCompression="XAS" GUIPreset="Default"/>

	<AudioFile id="NUOblite_VoiSelBata" File="SelectBattle\NUOblite_VoiSelBata.wav" PCCompression="XAS" GUIPreset="Default"/>
	<AudioFile id="NUOblite_VoiSelBatb" File="SelectBattle\NUOblite_VoiSelBatb.wav" PCCompression="XAS" GUIPreset="Default"/>
	<AudioFile id="NUOblite_VoiSelBatc" File="SelectBattle\NUOblite_VoiSelBatc.wav" PCCompression="XAS" GUIPreset="Default"/>
	<AudioFile id="NUOblite_VoiSelBatd" File="SelectBattle\NUOblite_VoiSelBatd.wav" PCCompression="XAS" GUIPreset="Default"/>
	<AudioFile id="NUOblite_VoiSelBate" File="SelectBattle\NUOblite_VoiSelBate.wav" PCCompression="XAS" GUIPreset="Default"/>
	<AudioFile id="NUOblite_VoiSelBatf" File="SelectBattle\NUOblite_VoiSelBatf.wav" PCCompression="XAS" GUIPreset="Default"/>
	<AudioFile id="NUOblite_VoiSelBatg" File="SelectBattle\NUOblite_VoiSelBatg.wav" PCCompression="XAS" GUIPreset="Default"/>
</AssetDeclaration>
